semantic_weaver-0.1.0.dist-info/licenses/LICENSE
semanticweaver/__init__.py
semanticweaver/weaver.py
semanticweaver/core/__init__.py
semanticweaver/core/auth.py
semanticweaver/core/transformer.py
semanticweaver/core/api/__init__.py
semanticweaver/core/api/fabric_client.py
semanticweaver/models/__init__.py
semanticweaver/models/base.py
semanticweaver/models/fabric.py
semanticweaver/models/intermediate.py
semanticweaver/plugins/__init__.py
semanticweaver/plugins/base.py
semanticweaver/plugins/databricks/__init__.py
semanticweaver/plugins/databricks/model.py
semanticweaver/plugins/databricks/plugin.py
semantic_weaver-0.1.0.dist-info/METADATA
semantic_weaver-0.1.0.dist-info/WHEEL
semantic_weaver-0.1.0.dist-info/top_level.txt
semantic_weaver-0.1.0.dist-info/RECORD
