Metadata-Version: 2.4
Name: semantic-weaver
Version: 0.1.0
Summary: Semantic Weaver is a Python library designed to migrate semantic model definitions from systems into Microsoft Fabric Semantic Models.
Author-email: Tonio Lora <tonio.lora@microsoft.com>, Tim Arif <timarif@microsoft.com>, Omer Ahmad <Omer.Ahmad@microsoft.com>
Project-URL: Homepage, https://github.com/microsoft/Semantic-Weaver
Project-URL: Documentation, https://github.com/microsoft/Semantic-Weaver/blob/main/docs/PolicyWeaver.md
Project-URL: Repository, https://github.com/microsoft/Semantic-Weaver.git
Project-URL: Issues, https://github.com/microsoft/Semantic-Weaver/issues
Keywords: Fabric,Fabric Semantic Model,Databricks,Looker,Power BI,Semantic Model,Migration
Requires-Python: >=3.11
License-File: LICENSE
Requires-Dist: databricks-sdk>=0.73.0
Requires-Dist: pydantic>=2.12.5
Requires-Dist: python-dotenv>=1.2.1
Requires-Dist: pyyaml>=6.0.3
Dynamic: license-file
